blu/__init__.py
blu/main.py
blu/commands/__init__.py
blu/commands/build.py
blu/commands/clean_up.py
blu/commands/deploy.py
blu/commands/gh_add.py
blu/commands/gh_create.py
blu/commands/gh_delete.py
blu/commands/gh_readme.py
blu/commands/linear.py
blu/constants/__init__.py
blu/utils/__init__.py
blu/utils/config.py
blu/utils/directories.py
blu/utils/docs.py
blu/utils/graphql_loader.py
blu/utils/run_command.py
blu_cli-0.1.0.dist-info/METADATA
blu_cli-0.1.0.dist-info/WHEEL
blu_cli-0.1.0.dist-info/entry_points.txt
blu_cli-0.1.0.dist-info/top_level.txt
blu_cli-0.1.0.dist-info/RECORD
