Metadata-Version: 2.2
Name: blu-cli
Version: 0.1.0
Summary: Automate the entire Software Development Lifecycle.
Home-page: https://github.com/dj-io/blu
Author: Stratum Labs
Author-email: hq@stratumlabs.ai
Project-URL: Code, https://github.com/dj-io/blu
Project-URL: Documentation, https://github.com/dj-io/blu/blob/main/blu-cli/README.md
Classifier: Programming Language :: Python :: 3
Classifier: License :: OSI Approved :: MIT License
Classifier: Operating System :: OS Independent
Classifier: Intended Audience :: Developers
Classifier: Topic :: Software Development :: Build Tools
Classifier: Topic :: Utilities
Requires-Python: >=3.7
Requires-Dist: questionary
Requires-Dist: click
Requires-Dist: python-dotenv
Requires-Dist: halo
Requires-Dist: flake8
Requires-Dist: black
Provides-Extra: dev
Requires-Dist: pytest; extra == "dev"
Dynamic: author
Dynamic: author-email
Dynamic: classifier
Dynamic: description
Dynamic: description-content-type
Dynamic: home-page
Dynamic: project-url
Dynamic: provides-extra
Dynamic: requires-dist
Dynamic: requires-python
Dynamic: summary
